firechannel/__init__.py
firechannel/channel.py
firechannel/credentials.py
firechannel/errors.py
firechannel/firebase.py
firechannel/pool.py
firechannel-0.6.0.dist-info/LICENSE
firechannel-0.6.0.dist-info/METADATA
firechannel-0.6.0.dist-info/WHEEL
firechannel-0.6.0.dist-info/top_level.txt
firechannel-0.6.0.dist-info/RECORD
