Metadata-Version: 2.1
Name: firechannel
Version: 0.6.0
Summary: An almost-dropin replacement for the GAE channels API using Firebase.
Home-page: https://github.com/leadpages/firechannel
Author: Leadpages
Author-email: opensource@leadpages.net
License: MIT
Platform: UNKNOWN
Classifier: Development Status :: 5 - Production/Stable
Classifier: Intended Audience :: Developers
Classifier: Topic :: Software Development :: Libraries
Classifier: License :: OSI Approved :: MIT License
Classifier: Programming Language :: Python :: 2
Classifier: Programming Language :: Python :: 2.7
Requires-Dist: requests (<3.0,>=2.18.4)
Requires-Dist: google-auth (<2.0,>=1.0)
